nc/__init__.py
nc/__main__.py
nc/color.py
nc/colors.py
nc/demo.py
nc/palette/__init__.py
nc/palette/_terminal256.py
nc/palette/html.py
nc/palette/juce.py
nc/palette/pwg.py
nc/palette/terminal16/__init__.py
nc/palette/terminal16/mirc.py
nc/palette/terminal16/putty.py
nc/palette/terminal16/terminal_app.py
nc/palette/terminal16/ubuntu.py
nc/palette/terminal16/vga.py
nc/palette/terminal16/visual_studio_code.py
nc/palette/terminal16/windows_10_console.py
nc/palette/terminal16/windows_console.py
nc/palette/terminal16/windows_powershell.py
nc/palette/terminal16/x.py
nc/palette/terminal16/xterm.py
nc/palette/terminal256.py
nc/palette/terminal8.py
nc/palette/wikipedia.py
nc/palette/x11.py
nc/terminal.py
nc-1.0.1.dist-info/LICENSE
nc-1.0.1.dist-info/WHEEL
nc-1.0.1.dist-info/METADATA
nc-1.0.1.dist-info/RECORD
